epi2melabs_splashpage/__init__.py
epi2melabs_splashpage/_version.py
epi2melabs_splashpage/labextension/build_log.json
epi2melabs_splashpage/labextension/package.json
epi2melabs_splashpage/labextension/schemas/@epi2melabs/epi2melabs-splashpage/package.json.orig
epi2melabs_splashpage/labextension/schemas/@epi2melabs/epi2melabs-splashpage/settings.json
epi2melabs_splashpage/labextension/static/lib_index_js.04ac4efcb5011272f5a3.js
epi2melabs_splashpage/labextension/static/lib_index_js.04ac4efcb5011272f5a3.js.map
epi2melabs_splashpage/labextension/static/node_modules_moment_locale_sync_recursive_.2f3f05dee5e404d6b3ee.js
epi2melabs_splashpage/labextension/static/node_modules_moment_locale_sync_recursive_.2f3f05dee5e404d6b3ee.js.map
epi2melabs_splashpage/labextension/static/remoteEntry.560ea03719907aa54126.js
epi2melabs_splashpage/labextension/static/remoteEntry.560ea03719907aa54126.js.map
epi2melabs_splashpage/labextension/static/style.js
epi2melabs_splashpage/labextension/static/style_index_js.50b225b38ec59f08060e.js
epi2melabs_splashpage/labextension/static/style_index_js.50b225b38ec59f08060e.js.map
epi2melabs_splashpage/labextension/static/vendors-node_modules_css-loader_dist_runtime_api_js-node_modules_css-loader_dist_runtime_cssW-926fd9.2d454ee45168ac186189.js
epi2melabs_splashpage/labextension/static/vendors-node_modules_css-loader_dist_runtime_api_js-node_modules_css-loader_dist_runtime_cssW-926fd9.2d454ee45168ac186189.js.map
epi2melabs_splashpage/labextension/static/vendors-node_modules_moment_locale_af_js-node_modules_moment_locale_ar-dz_js-node_modules_mom-248d90.dc3dcc9b72d9543ebe0e.js
epi2melabs_splashpage/labextension/static/vendors-node_modules_moment_locale_af_js-node_modules_moment_locale_ar-dz_js-node_modules_mom-248d90.dc3dcc9b72d9543ebe0e.js.map
epi2melabs_splashpage-1.0.0.data/data/share/jupyter/labextensions/@epi2melabs/epi2melabs-splashpage/build_log.json
epi2melabs_splashpage-1.0.0.dist-info/LICENSE
epi2melabs_splashpage-1.0.0.dist-info/METADATA
epi2melabs_splashpage-1.0.0.dist-info/WHEEL
epi2melabs_splashpage-1.0.0.dist-info/top_level.txt
epi2melabs_splashpage-1.0.0.dist-info/RECORD
