Metadata-Version: 2.1
Name: epi2melabs-splashpage
Version: 1.0.0
Summary: Accompanies the EPI2ME labs experience. Not for general use.
Home-page: https://github.com/epi2me-labs/epi2melabs-splashpage
Author: trich
License: BSD-3-Clause
Keywords: Jupyter,JupyterLab,JupyterLab3
Platform: Linux
Platform: Mac OS X
Platform: Windows
Classifier: License :: OSI Approved :: BSD License
Classifier: Programming Language :: Python
Classifier: Programming Language :: Python :: 3
Classifier: Programming Language :: Python :: 3.6
Classifier: Programming Language :: Python :: 3.7
Classifier: Programming Language :: Python :: 3.8
Classifier: Programming Language :: Python :: 3.9
Classifier: Framework :: Jupyter
Requires-Python: >=3.6
Requires-Dist: jupyter-server (<2,>=1.6)
